watson_text_talker/__init__.py
watson_text_talker/watson_text_talker.py
watson_text_talker-0.8.10.dist-info/METADATA
watson_text_talker-0.8.10.dist-info/RECORD
watson_text_talker-0.8.10.dist-info/WHEEL
watson_text_talker-0.8.10.dist-info/top_level.txt
