Metadata-Version: 2.1
Name: watson-text-talker
Version: 0.8.10
Summary: Simple Text-to-Speech Interface for Raspberry Pi using IBM's Watson TTS
Home-page: https://github.com/ziligy/watson-text-talker
Author: Jeff Greenberg
Author-email: jeff@ziligy.com
License: MIT
Platform: UNKNOWN
Classifier: Programming Language :: Python :: 3
Classifier: Topic :: Home Automation
Classifier: Topic :: Multimedia :: Sound/Audio :: Speech
Classifier: Intended Audience :: Developers
Classifier: License :: OSI Approved :: MIT License
Classifier: Operating System :: OS Independent
Requires-Dist: watson-developer-cloud
Requires-Dist: pygame
Requires-Dist: python-slugify
